example/Decoder.v
module Decoder(
    input reset,
    input [2:0] S,
    output reg [7:0] out
);
    always @*
    begin
        if(reset == 1'b1)
            out = 8'b00000000;
        else
        begin
            case(S)
                3'b000: out = 8'b00000001;
                3'b001: out = 8'b00000010;
                3'b010: out = 8'b00000100;
                3'b011: out = 8'b00001000;
                3'b100: out = 8'b00010000;
                3'b101: out = 8'b00100000;
                3'b110: out = 8'b01000000;
                3'b111: out = 8'b10000000;
            endcase
        end
    end
endmodule

example/Decoder.vcd
$version Generated by VerilatedVcd $end
$date Fri Apr 15 15:13:18 2022
 $end
$timescale   1ns $end

 $scope module TOP $end
  $var wire  3 + S [2:0] $end
  $var wire  8 3 out [7:0] $end
  $var wire  1 # reset $end
  $scope module Decoder $end
   $var wire  3 + S [2:0] $end
   $var wire  8 3 out [7:0] $end
   $var wire  1 # reset $end
  $upscope $end
 $upscope $end
$enddefinitions $end


#0
0#
b000 +
b00000001 3
#1
b001 +
b00000010 3
#2
b010 +
b00000100 3
#3
b011 +
b00001000 3
#4
b100 +
b00010000 3
#5
b101 +
b00100000 3
#6
b110 +
b01000000 3
#7
b111 +
b10000000 3
#8
b000 +
b00000000 3
#9
b001 +
#10
b010 +
#11
b011 +
#12
b100 +
#13
b101 +
#14
b110 +
#15
b111 +
#16
b000 +
#17
b001 +
#18
b010 +
#19
b011 +
#20
b100 +
#21
b101 +
#22
b110 +
#23
b111 +
#24
b000 +
#25
b001 +
#26
b010 +
#27
b011 +
#28
b100 +
#29
b101 +
#30
b110 +
#31
b111 +
#32
b000 +
#33
b001 +
#34
b010 +
#35
b011 +
#36
b100 +
#37
b101 +
#38
b110 +
#39
b111 +
#40
b000 +
#41
b001 +
#42
b010 +
#43
b011 +
#44
b100 +
#45
b101 +
#46
b110 +
#47
b111 +
#48
b000 +
#49
b001 +
#50
b010 +
#51
b011 +
#52
b100 +
#53
b101 +
#54
b110 +
#55
b111 +
#56
b000 +
#57
b001 +
#58
b010 +
#59
b011 +
#60
b100 +
#61
b101 +
#62
b110 +
#63
b111 +
#64
b000 +
#65
b001 +
#66
b010 +
#67
b011 +
#68
b100 +
#69
b101 +
#70
b110 +
#71
b111 +
#72
b000 +
#73
b001 +
#74
b010 +
#75
b011 +
#76
b100 +
#77
b101 +
#78
b110 +
#79
b111 +
#80
b000 +
#81
b001 +
#82
b010 +
#83
b011 +
#84
b100 +
#85
b101 +
#86
b110 +
#87
b111 +
#88
b000 +
#89
b001 +
#90
b010 +
#91
b011 +
#92
b100 +
#93
b101 +
#94
b110 +
#95
b111 +
#96
b000 +
#97
b001 +
#98
b010 +
#99
b011 +
#100
b100 +
#101
b101 +
#102
b110 +
#103
b111 +
#104
b000 +
#105
b001 +
#106
b010 +
#107
b011 +
#108
b100 +
#109
b101 +
#110
b110 +
#111
b111 +
#112
b000 +
#113
b001 +
#114
b010 +
#115
b011 +
#116
b100 +
#117
b101 +
#118
b110 +
#119
b111 +
#120
b000 +
#121
b001 +
#122
b010 +
#123
b011 +
#124
b100 +
#125
b101 +
#126
b110 +
#127
b111 +
#128
b000 +
b00000001 3
#129
b001 +
b00000010 3
#130
b010 +
b00000100 3
#131
b011 +
b00001000 3
#132
b100 +
b00010000 3
#133
b101 +
b00100000 3
#134
b110 +
b01000000 3
#135
b111 +
b10000000 3
#136
b000 +
b00000000 3
#137
b001 +
#138
b010 +
#139
b011 +
#140
b100 +
#141
b101 +
#142
b110 +
#143
b111 +
#144
b000 +
#145
b001 +
#146
b010 +
#147
b011 +
#148
b100 +
#149
b101 +
#150
b110 +
#151
b111 +
#152
b000 +
#153
b001 +
#154
b010 +
#155
b011 +
#156
b100 +
#157
b101 +
#158
b110 +
#159
b111 +
#160
b000 +
#161
b001 +
#162
b010 +
#163
b011 +
#164
b100 +
#165
b101 +
#166
b110 +
#167
b111 +
#168
b000 +
#169
b001 +
#170
b010 +
#171
b011 +
#172
b100 +
#173
b101 +
#174
b110 +
#175
b111 +
#176
b000 +
#177
b001 +
#178
b010 +
#179
b011 +
#180
b100 +
#181
b101 +
#182
b110 +
#183
b111 +
#184
b000 +
#185
b001 +
#186
b010 +
#187
b011 +
#188
b100 +
#189
b101 +
#190
b110 +
#191
b111 +
#192
b000 +
#193
b001 +
#194
b010 +
#195
b011 +
#196
b100 +
#197
b101 +
#198
b110 +
#199
b111 +
#200
b000 +
#201
b001 +
#202
b010 +
#203
b011 +
#204
b100 +
#205
b101 +
#206
b110 +
#207
b111 +
#208
b000 +
#209
b001 +
#210
b010 +
#211
b011 +
#212
b100 +
#213
b101 +
#214
b110 +
#215
b111 +
#216
b000 +
#217
b001 +
#218
b010 +
#219
b011 +
#220
b100 +
#221
b101 +
#222
b110 +
#223
b111 +
#224
b000 +
#225
b001 +
#226
b010 +
#227
b011 +
#228
b100 +
#229
b101 +
#230
b110 +
#231
b111 +
#232
b000 +
#233
b001 +
#234
b010 +
#235
b011 +
#236
b100 +
#237
b101 +
#238
b110 +
#239
b111 +
#240
b000 +
#241
b001 +
#242
b010 +
#243
b011 +
#244
b100 +
#245
b101 +
#246
b110 +
#247
b111 +
#248
b000 +
#249
b001 +
#250
b010 +
#251
b011 +
#252
b100 +
#253
b101 +
#254
b110 +
#255
b111 +
#256
b000 +
b00000001 3
#257
b001 +
b00000010 3
#258
b010 +
b00000100 3
#259
b011 +
b00001000 3
#260
b100 +
b00010000 3
#261
b101 +
b00100000 3
#262
b110 +
b01000000 3
#263
b111 +
b10000000 3
#264
b000 +
b00000000 3
#265
b001 +
#266
b010 +
#267
b011 +
#268
b100 +
#269
b101 +
#270
b110 +
#271
b111 +
#272
b000 +
#273
b001 +
#274
b010 +
#275
b011 +
#276
b100 +
#277
b101 +
#278
b110 +
#279
b111 +
#280
b000 +
#281
b001 +
#282
b010 +
#283
b011 +
#284
b100 +
#285
b101 +
#286
b110 +
#287
b111 +
#288
b000 +
#289
b001 +
#290
b010 +
#291
b011 +
#292
b100 +
#293
b101 +
#294
b110 +
#295
b111 +
#296
b000 +
#297
b001 +
#298
b010 +
#299
b011 +
#300
b100 +
#301
b101 +
#302
b110 +
#303
b111 +
#304
b000 +
#305
b001 +
#306
b010 +
#307
b011 +
#308
b100 +
#309
b101 +
#310
b110 +
#311
b111 +
#312
b000 +
#313
b001 +
#314
b010 +
#315
b011 +
#316
b100 +
#317
b101 +
#318
b110 +
#319
b111 +
#320
b000 +
#321
b001 +
#322
b010 +
#323
b011 +
#324
b100 +
#325
b101 +
#326
b110 +
#327
b111 +
#328
b000 +
#329
b001 +
#330
b010 +
#331
b011 +
#332
b100 +
#333
b101 +
#334
b110 +
#335
b111 +
#336
b000 +
#337
b001 +
#338
b010 +
#339
b011 +
#340
b100 +
#341
b101 +
#342
b110 +
#343
b111 +
#344
b000 +
#345
b001 +
#346
b010 +
#347
b011 +
#348
b100 +
#349
b101 +
#350
b110 +
#351
b111 +
#352
b000 +
#353
b001 +
#354
b010 +
#355
b011 +
#356
b100 +
#357
b101 +
#358
b110 +
#359
b111 +
#360
b000 +
#361
b001 +
#362
b010 +
#363
b011 +
#364
b100 +
#365
b101 +
#366
b110 +
#367
b111 +
#368
b000 +
#369
b001 +
#370
b010 +
#371
b011 +
#372
b100 +
#373
b101 +
#374
b110 +
#375
b111 +
#376
b000 +
#377
b001 +
#378
b010 +
#379
b011 +
#380
b100 +
#381
b101 +
#382
b110 +
#383
b111 +
#384
b000 +
b00000001 3
#385
b001 +
b00000010 3
#386
b010 +
b00000100 3
#387
b011 +
b00001000 3
#388
b100 +
b00010000 3
#389
b101 +
b00100000 3
#390
b110 +
b01000000 3
#391
b111 +
b10000000 3
#392
b000 +
b00000000 3
#393
b001 +
#394
b010 +
#395
b011 +
#396
b100 +
#397
b101 +
#398
b110 +
#399
b111 +
#400
b000 +
#401
b001 +
#402
b010 +
#403
b011 +
#404
b100 +
#405
b101 +
#406
b110 +
#407
b111 +
#408
b000 +
#409
b001 +
#410
b010 +
#411
b011 +
#412
b100 +
#413
b101 +
#414
b110 +
#415
b111 +
#416
b000 +
#417
b001 +
#418
b010 +
#419
b011 +
#420
b100 +
#421
b101 +
#422
b110 +
#423
b111 +
#424
b000 +
#425
b001 +
#426
b010 +
#427
b011 +
#428
b100 +
#429
b101 +
#430
b110 +
#431
b111 +
#432
b000 +
#433
b001 +
#434
b010 +
#435
b011 +
#436
b100 +
#437
b101 +
#438
b110 +
#439
b111 +
#440
b000 +
#441
b001 +
#442
b010 +
#443
b011 +
#444
b100 +
#445
b101 +
#446
b110 +
#447
b111 +
#448
b000 +
#449
b001 +
#450
b010 +
#451
b011 +
#452
b100 +
#453
b101 +
#454
b110 +
#455
b111 +
#456
b000 +
#457
b001 +
#458
b010 +
#459
b011 +
#460
b100 +
#461
b101 +
#462
b110 +
#463
b111 +
#464
b000 +
#465
b001 +
#466
b010 +
#467
b011 +
#468
b100 +
#469
b101 +
#470
b110 +
#471
b111 +
#472
b000 +
#473
b001 +
#474
b010 +
#475
b011 +
#476
b100 +
#477
b101 +
#478
b110 +
#479
b111 +
#480
b000 +
#481
b001 +
#482
b010 +
#483
b011 +
#484
b100 +
#485
b101 +
#486
b110 +
#487
b111 +
#488
b000 +
#489
b001 +
#490
b010 +
#491
b011 +
#492
b100 +
#493
b101 +
#494
b110 +
#495
b111 +
#496
b000 +
#497
b001 +
#498
b010 +
#499
b011 +
#500
b100 +
#501
b101 +
#502
b110 +
#503
b111 +
#504
b000 +
#505
b001 +
#506
b010 +
#507
b011 +
#508
b100 +
#509
b101 +
#510
b110 +
#511
b111 +
#512
b000 +
b00000001 3
#513
b001 +
b00000010 3
#514
b010 +
b00000100 3
#515
b011 +
b00001000 3
#516
b100 +
b00010000 3
#517
b101 +
b00100000 3
#518
b110 +
b01000000 3
#519
b111 +
b10000000 3
#520
b000 +
b00000000 3
#521
b001 +
#522
b010 +
#523
b011 +
#524
b100 +
#525
b101 +
#526
b110 +
#527
b111 +
#528
b000 +
#529
b001 +
#530
b010 +
#531
b011 +
#532
b100 +
#533
b101 +
#534
b110 +
#535
b111 +
#536
b000 +
#537
b001 +
#538
b010 +
#539
b011 +
#540
b100 +
#541
b101 +
#542
b110 +
#543
b111 +
#544
b000 +
#545
b001 +
#546
b010 +
#547
b011 +
#548
b100 +
#549
b101 +
#550
b110 +
#551
b111 +
#552
b000 +
#553
b001 +
#554
b010 +
#555
b011 +
#556
b100 +
#557
b101 +
#558
b110 +
#559
b111 +
#560
b000 +
#561
b001 +
#562
b010 +
#563
b011 +
#564
b100 +
#565
b101 +
#566
b110 +
#567
b111 +
#568
b000 +
#569
b001 +
#570
b010 +
#571
b011 +
#572
b100 +
#573
b101 +
#574
b110 +
#575
b111 +
#576
b000 +
#577
b001 +
#578
b010 +
#579
b011 +
#580
b100 +
#581
b101 +
#582
b110 +
#583
b111 +
#584
b000 +
#585
b001 +
#586
b010 +
#587
b011 +
#588
b100 +
#589
b101 +
#590
b110 +
#591
b111 +
#592
b000 +
#593
b001 +
#594
b010 +
#595
b011 +
#596
b100 +
#597
b101 +
#598
b110 +
#599
b111 +
#600
b000 +
#601
b001 +
#602
b010 +
#603
b011 +
#604
b100 +
#605
b101 +
#606
b110 +
#607
b111 +
#608
b000 +
#609
b001 +
#610
b010 +
#611
b011 +
#612
b100 +
#613
b101 +
#614
b110 +
#615
b111 +
#616
b000 +
#617
b001 +
#618
b010 +
#619
b011 +
#620
b100 +
#621
b101 +
#622
b110 +
#623
b111 +
#624
b000 +
#625
b001 +
#626
b010 +
#627
b011 +
#628
b100 +
#629
b101 +
#630
b110 +
#631
b111 +
#632
b000 +
#633
b001 +
#634
b010 +
#635
b011 +
#636
b100 +
#637
b101 +
#638
b110 +
#639
b111 +
#640
b000 +
b00000001 3
#641
b001 +
b00000010 3
#642
b010 +
b00000100 3
#643
b011 +
b00001000 3
#644
b100 +
b00010000 3
#645
b101 +
b00100000 3
#646
b110 +
b01000000 3
#647
b111 +
b10000000 3
#648
b000 +
b00000000 3
#649
b001 +
#650
b010 +
#651
b011 +
#652
b100 +
#653
b101 +
#654
b110 +
#655
b111 +
#656
b000 +
#657
b001 +
#658
b010 +
#659
b011 +
#660
b100 +
#661
b101 +
#662
b110 +
#663
b111 +
#664
b000 +
#665
b001 +
#666
b010 +
#667
b011 +
#668
b100 +
#669
b101 +
#670
b110 +
#671
b111 +
#672
b000 +
#673
b001 +
#674
b010 +
#675
b011 +
#676
b100 +
#677
b101 +
#678
b110 +
#679
b111 +
#680
b000 +
#681
b001 +
#682
b010 +
#683
b011 +
#684
b100 +
#685
b101 +
#686
b110 +
#687
b111 +
#688
b000 +
#689
b001 +
#690
b010 +
#691
b011 +
#692
b100 +
#693
b101 +
#694
b110 +
#695
b111 +
#696
b000 +
#697
b001 +
#698
b010 +
#699
b011 +
#700
b100 +
#701
b101 +
#702
b110 +
#703
b111 +
#704
b000 +
#705
b001 +
#706
b010 +
#707
b011 +
#708
b100 +
#709
b101 +
#710
b110 +
#711
b111 +
#712
b000 +
#713
b001 +
#714
b010 +
#715
b011 +
#716
b100 +
#717
b101 +
#718
b110 +
#719
b111 +
#720
b000 +
#721
b001 +
#722
b010 +
#723
b011 +
#724
b100 +
#725
b101 +
#726
b110 +
#727
b111 +
#728
b000 +
#729
b001 +
#730
b010 +
#731
b011 +
#732
b100 +
#733
b101 +
#734
b110 +
#735
b111 +
#736
b000 +
#737
b001 +
#738
b010 +
#739
b011 +
#740
b100 +
#741
b101 +
#742
b110 +
#743
b111 +
#744
b000 +
#745
b001 +
#746
b010 +
#747
b011 +
#748
b100 +
#749
b101 +
#750
b110 +
#751
b111 +
#752
b000 +
#753
b001 +
#754
b010 +
#755
b011 +
#756
b100 +
#757
b101 +
#758
b110 +
#759
b111 +
#760
b000 +
#761
b001 +
#762
b010 +
#763
b011 +
#764
b100 +
#765
b101 +
#766
b110 +
#767
b111 +
#768
b000 +
b00000001 3
#769
b001 +
b00000010 3
#770
b010 +
b00000100 3
#771
b011 +
b00001000 3
#772
b100 +
b00010000 3
#773
b101 +
b00100000 3
#774
b110 +
b01000000 3
#775
b111 +
b10000000 3
#776
b000 +
b00000000 3
#777
b001 +
#778
b010 +
#779
b011 +
#780
b100 +
#781
b101 +
#782
b110 +
#783
b111 +
#784
b000 +
#785
b001 +
#786
b010 +
#787
b011 +
#788
b100 +
#789
b101 +
#790
b110 +
#791
b111 +
#792
b000 +
#793
b001 +
#794
b010 +
#795
b011 +
#796
b100 +
#797
b101 +
#798
b110 +
#799
b111 +
#800
b000 +
#801
b001 +
#802
b010 +
#803
b011 +
#804
b100 +
#805
b101 +
#806
b110 +
#807
b111 +
#808
b000 +
#809
b001 +
#810
b010 +
#811
b011 +
#812
b100 +
#813
b101 +
#814
b110 +
#815
b111 +
#816
b000 +
#817
b001 +
#818
b010 +
#819
b011 +
#820
b100 +
#821
b101 +
#822
b110 +
#823
b111 +
#824
b000 +
#825
b001 +
#826
b010 +
#827
b011 +
#828
b100 +
#829
b101 +
#830
b110 +
#831
b111 +
#832
b000 +
#833
b001 +
#834
b010 +
#835
b011 +
#836
b100 +
#837
b101 +
#838
b110 +
#839
b111 +
#840
b000 +
#841
b001 +
#842
b010 +
#843
b011 +
#844
b100 +
#845
b101 +
#846
b110 +
#847
b111 +
#848
b000 +
#849
b001 +
#850
b010 +
#851
b011 +
#852
b100 +
#853
b101 +
#854
b110 +
#855
b111 +
#856
b000 +
#857
b001 +
#858
b010 +
#859
b011 +
#860
b100 +
#861
b101 +
#862
b110 +
#863
b111 +
#864
b000 +
#865
b001 +
#866
b010 +
#867
b011 +
#868
b100 +
#869
b101 +
#870
b110 +
#871
b111 +
#872
b000 +
#873
b001 +
#874
b010 +
#875
b011 +
#876
b100 +
#877
b101 +
#878
b110 +
#879
b111 +
#880
b000 +
#881
b001 +
#882
b010 +
#883
b011 +
#884
b100 +
#885
b101 +
#886
b110 +
#887
b111 +
#888
b000 +
#889
b001 +
#890
b010 +
#891
b011 +
#892
b100 +
#893
b101 +
#894
b110 +
#895
b111 +
#896
b000 +
b00000001 3
#897
b001 +
b00000010 3
#898
b010 +
b00000100 3
#899
b011 +
b00001000 3
#900
b100 +
b00010000 3
#901
b101 +
b00100000 3
#902
b110 +
b01000000 3
#903
b111 +
b10000000 3
#904
b000 +
b00000000 3
#905
b001 +
#906
b010 +
#907
b011 +
#908
b100 +
#909
b101 +
#910
b110 +
#911
b111 +
#912
b000 +
#913
b001 +
#914
b010 +
#915
b011 +
#916
b100 +
#917
b101 +
#918
b110 +
#919
b111 +
#920
b000 +
#921
b001 +
#922
b010 +
#923
b011 +
#924
b100 +
#925
b101 +
#926
b110 +
#927
b111 +
#928
b000 +
#929
b001 +
#930
b010 +
#931
b011 +
#932
b100 +
#933
b101 +
#934
b110 +
#935
b111 +
#936
b000 +
#937
b001 +
#938
b010 +
#939
b011 +
#940
b100 +
#941
b101 +
#942
b110 +
#943
b111 +
#944
b000 +
#945
b001 +
#946
b010 +
#947
b011 +
#948
b100 +
#949
b101 +
#950
b110 +
#951
b111 +
#952
b000 +
#953
b001 +
#954
b010 +
#955
b011 +
#956
b100 +
#957
b101 +
#958
b110 +
#959
b111 +
#960
b000 +
#961
b001 +
#962
b010 +
#963
b011 +
#964
b100 +
#965
b101 +
#966
b110 +
#967
b111 +
#968
b000 +
#969
b001 +
#970
b010 +
#971
b011 +
#972
b100 +
#973
b101 +
#974
b110 +
#975
b111 +
#976
b000 +
#977
b001 +
#978
b010 +
#979
b011 +
#980
b100 +
#981
b101 +
#982
b110 +
#983
b111 +
#984
b000 +
#985
b001 +
#986
b010 +
#987
b011 +
#988
b100 +
#989
b101 +
#990
b110 +
#991
b111 +
#992
b000 +
#993
b001 +
#994
b010 +
#995
b011 +
#996
b100 +
#997
b101 +
#998
b110 +
#999
b111 +
#1000
b000 +
#1001
b001 +
#1002
b010 +
#1003
b011 +
#1004
b100 +
#1005
b101 +
#1006
b110 +
#1007
b111 +
#1008
b000 +
#1009
b001 +
#1010
b010 +
#1011
b011 +
#1012
b100 +
#1013
b101 +
#1014
b110 +
#1015
b111 +
#1016
b000 +
#1017
b001 +
#1018
b010 +
#1019
b011 +
#1020
b100 +
#1021
b101 +
#1022
b110 +
#1023
b111 +
